zdz-0.1.0.dist-info/METADATA
zdz-0.1.0.dist-info/WHEEL
zdz-0.1.0.dist-info/license_files/LICENSE
zdz/__init__.py
zdz/zdz.cpython-39-x86_64-linux-gnu.so
zdz-0.1.0.dist-info/RECORD
