Metadata-Version: 2.1
Name: zdz
Version: 0.1.0
License-File: LICENSE
Summary: utils tools for zdz
Keywords: zdz,tools
Author: zdz
Author-email: doge.py@gmail.com
Maintainer-email: zdz <doge.py@gmail.com>
License: Apache-2.0
Requires-Python: >=3.9
